normalpyrunner.py
NormalPyRunner-0.1.2.dist-info/METADATA
NormalPyRunner-0.1.2.dist-info/WHEEL
NormalPyRunner-0.1.2.dist-info/top_level.txt
NormalPyRunner-0.1.2.dist-info/RECORD
