Metadata-Version: 2.1
Name: NormalPyRunner
Version: 0.1.2
